html5builder.py
html5builder-0.1.0.dist-info/LICENSE
html5builder-0.1.0.dist-info/METADATA
html5builder-0.1.0.dist-info/WHEEL
html5builder-0.1.0.dist-info/top_level.txt
html5builder-0.1.0.dist-info/RECORD
