Metadata-Version: 2.1
Name: html5builder
Version: 0.1.0
Summary: Simple HTML5 document builder.
Home-page: https://github.com/skitschy/pyHTML5builder
Author: skitschy
Author-email: s1kitschy@gmail.com
License: MIT
Project-URL: Documentation, https://pyhtml5builder.readthedocs.io/
Project-URL: Source, https://github.com/skitschy/pyHTML5builder
Keywords: html5
Platform: UNKNOWN
Classifier: Development Status :: 5 - Production/Stable
Classifier: License :: OSI Approved :: MIT License
Classifier: Intended Audience :: Developers
Classifier: Operating System :: OS Independent
Classifier: Programming Language :: Python
Classifier: Programming Language :: Python :: 2
Classifier: Programming Language :: Python :: 2.7
Classifier: Programming Language :: Python :: 3
Classifier: Programming Language :: Python :: 3.3
Classifier: Programming Language :: Python :: 3.5
Classifier: Programming Language :: Python :: 3.6
Classifier: Programming Language :: Python :: 3.7
Classifier: Topic :: Text Processing :: Markup :: HTML
Requires-Python: >=2.7, !=3.0.*
